comproscanner/__init__.py
comproscanner/comproscanner.py
comproscanner/data_visualizer.py
comproscanner/eval_visualizer.py
comproscanner/article_processors/__init__.py
comproscanner/article_processors/elsevier_processor.py
comproscanner/article_processors/iop_processor.py
comproscanner/article_processors/pdfs_processor.py
comproscanner/article_processors/springer_processor.py
comproscanner/article_processors/wiley_processor.py
comproscanner/extract_flow/__init__.py
comproscanner/extract_flow/main_extraction_flow.py
comproscanner/extract_flow/crews/composition_crew/composition_extraction_crew/composition_extraction_crew.py
comproscanner/extract_flow/crews/composition_crew/composition_format_crew/composition_format_crew.py
comproscanner/extract_flow/crews/materials_data_identifier_crew/materials_data_identifier_crew.py
comproscanner/extract_flow/crews/synthesis_crew/synthesis_extraction_crew/synthesis_extraction_crew.py
comproscanner/extract_flow/crews/synthesis_crew/synthesis_format_crew/synthesis_format_crew.py
comproscanner/extract_flow/tools/__init__.py
comproscanner/extract_flow/tools/material_parser_tool.py
comproscanner/extract_flow/tools/rag_tool.py
comproscanner/metadata_extractor/__init__.py
comproscanner/metadata_extractor/fetch_metadata.py
comproscanner/metadata_extractor/filter_metadata.py
comproscanner/post_processing/data_cleaner.py
comproscanner/post_processing/evaluation/semantic_evaluator.py
comproscanner/post_processing/evaluation/eval_flow/eval_flow.py
comproscanner/post_processing/evaluation/eval_flow/crews/composition_evaluation_crew/composition_evaluation_crew.py
comproscanner/post_processing/evaluation/eval_flow/crews/synthesis_evaluation_crew/synthesis_evaluation_crew.py
comproscanner/post_processing/visualization/create_knowledge_graph.py
comproscanner/post_processing/visualization/data_distribution_visualizers.py
comproscanner/post_processing/visualization/eval_plot_visualizers.py
comproscanner/utils/__init__.py
comproscanner-0.1.3.dist-info/licenses/LICENSE
comproscanner-0.1.3.dist-info/METADATA
comproscanner-0.1.3.dist-info/WHEEL
comproscanner-0.1.3.dist-info/top_level.txt
comproscanner-0.1.3.dist-info/RECORD
