Metadata-Version: 2.4
Name: comproscanner
Version: 0.1.3
Summary: Multi-agent system for extracting and processing structured composition-property data from scientific literature
Author-email: Aritra Roy <contact@aritraroy.live>
License: MIT
Project-URL: Homepage, https://github.com/slimeslab/ComProScanner
Project-URL: Bug Tracker, https://github.com/slimeslab/ComProScanner/issues
Classifier: Development Status :: 3 - Alpha
Classifier: Intended Audience :: Developers
Classifier: Intended Audience :: Science/Research
Classifier: License :: OSI Approved :: MIT License
Classifier: Operating System :: OS Independent
Classifier: Programming Language :: Python :: 3
Classifier: Programming Language :: Python :: 3.12
Classifier: Topic :: Scientific/Engineering
Classifier: Topic :: Scientific/Engineering :: Chemistry
Classifier: Topic :: Scientific/Engineering :: Physics
Classifier: Topic :: Scientific/Engineering :: Artificial Intelligence
Classifier: Topic :: Scientific/Engineering :: Information Analysis
Classifier: Topic :: Scientific/Engineering :: Visualization
Requires-Python: <3.14,>=3.12
License-File: LICENSE
Requires-Dist: requests
Requires-Dist: python-dotenv
Requires-Dist: tqdm
Requires-Dist: lxml
Requires-Dist: pandas
Requires-Dist: torch
Requires-Dist: langchain
Requires-Dist: transformers
Requires-Dist: tokenizers
Requires-Dist: mysql
Requires-Dist: mysql-connector
Requires-Dist: langchain_community
Requires-Dist: crewai
Requires-Dist: crewai-tools
Requires-Dist: chromadb
Requires-Dist: docling
Requires-Dist: sentence-transformers
Requires-Dist: neo4j
Requires-Dist: pymatgen
Requires-Dist: seaborn
Provides-Extra: dev
Requires-Dist: pytest; extra == "dev"
Requires-Dist: pytest-mock; extra == "dev"
Provides-Extra: docs
Requires-Dist: mkdocs-material; extra == "docs"
Requires-Dist: mkdocs-minify-plugin; extra == "docs"
Dynamic: license-file
